DataDocking/__init__.py
DataDocking/data_restframework.py
PoolDB/PoolDB.py
PoolDB/__init__.py
PoolDB/readme.md
PoolDB-0.0.5.dist-info/LICENSE
PoolDB-0.0.5.dist-info/METADATA
PoolDB-0.0.5.dist-info/WHEEL
PoolDB-0.0.5.dist-info/top_level.txt
PoolDB-0.0.5.dist-info/RECORD
