Metadata-Version: 2.1
Name: PoolDB
Version: 0.0.5
Summary: Pool DB package
Home-page: https://github.com/AlitaIcon/PoolDB
Author: alita
Author-email: 1906321518@qq.com
License: MIT
Project-URL: Documentation, https://github.com/AlitaIcon/PoolDB
Platform: UNKNOWN
Classifier: Programming Language :: Python :: 3
Classifier: License :: OSI Approved :: MIT License
Classifier: Operating System :: OS Independent
Requires-Python: >=3.6
Requires-Dist: SQLAlchemy (>=1.3.19)
Requires-Dist: gevent (>=21.1.2)
Requires-Dist: loguru (>=0.5.3)
Requires-Dist: gevent (>=21.8.0)
Requires-Dist: pandas (>=1.1.5)
